odoo/addons/membership_initial_fee/README.rst
odoo/addons/membership_initial_fee/__init__.py
odoo/addons/membership_initial_fee/__manifest__.py
odoo/addons/membership_initial_fee/i18n/ar.po
odoo/addons/membership_initial_fee/i18n/bs.po
odoo/addons/membership_initial_fee/i18n/ca.po
odoo/addons/membership_initial_fee/i18n/cs.po
odoo/addons/membership_initial_fee/i18n/de.po
odoo/addons/membership_initial_fee/i18n/en_GB.po
odoo/addons/membership_initial_fee/i18n/es.po
odoo/addons/membership_initial_fee/i18n/es_CR.po
odoo/addons/membership_initial_fee/i18n/es_EC.po
odoo/addons/membership_initial_fee/i18n/es_MX.po
odoo/addons/membership_initial_fee/i18n/et.po
odoo/addons/membership_initial_fee/i18n/fi.po
odoo/addons/membership_initial_fee/i18n/fr.po
odoo/addons/membership_initial_fee/i18n/fr_CH.po
odoo/addons/membership_initial_fee/i18n/hr.po
odoo/addons/membership_initial_fee/i18n/hr_HR.po
odoo/addons/membership_initial_fee/i18n/hu.po
odoo/addons/membership_initial_fee/i18n/it.po
odoo/addons/membership_initial_fee/i18n/ja.po
odoo/addons/membership_initial_fee/i18n/lt.po
odoo/addons/membership_initial_fee/i18n/membership_initial_fee.pot
odoo/addons/membership_initial_fee/i18n/mk.po
odoo/addons/membership_initial_fee/i18n/mn.po
odoo/addons/membership_initial_fee/i18n/nb.po
odoo/addons/membership_initial_fee/i18n/nl.po
odoo/addons/membership_initial_fee/i18n/nl_BE.po
odoo/addons/membership_initial_fee/i18n/nl_NL.po
odoo/addons/membership_initial_fee/i18n/pt.po
odoo/addons/membership_initial_fee/i18n/pt_BR.po
odoo/addons/membership_initial_fee/i18n/pt_PT.po
odoo/addons/membership_initial_fee/i18n/ro.po
odoo/addons/membership_initial_fee/i18n/ru.po
odoo/addons/membership_initial_fee/i18n/sl.po
odoo/addons/membership_initial_fee/i18n/sv.po
odoo/addons/membership_initial_fee/i18n/tr.po
odoo/addons/membership_initial_fee/i18n/tr_TR.po
odoo/addons/membership_initial_fee/i18n/vi_VN.po
odoo/addons/membership_initial_fee/i18n/zh_CN.po
odoo_addon_membership_initial_fee-18.0.1.0.0.2.dist-info/METADATA
odoo_addon_membership_initial_fee-18.0.1.0.0.2.dist-info/WHEEL
odoo_addon_membership_initial_fee-18.0.1.0.0.2.dist-info/top_level.txt
odoo_addon_membership_initial_fee-18.0.1.0.0.2.dist-info/RECORD
